{
  "generated_at": "2026-07-04",
  "source": "media-library",
  "note": "Generated by media-library/scripts/export-collect-watching.mjs. Do not hand-edit.",
  "top_movies": [
    {
      "title": "Fargo",
      "year": 1996,
      "score": 9.7,
      "type": "film",
      "tmdb_url": "https://www.themoviedb.org/movie/275"
    },
    {
      "title": "The Handmaiden",
      "year": 2016,
      "score": 9.6,
      "type": "film",
      "tmdb_url": "https://www.themoviedb.org/movie/290098"
    },
    {
      "title": "There Will Be Blood",
      "year": 2007,
      "score": 9.6,
      "type": "film",
      "tmdb_url": "https://www.themoviedb.org/movie/7345"
    },
    {
      "title": "Inglourious Basterds",
      "year": 2009,
      "score": 9.6,
      "type": "film",
      "tmdb_url": "https://www.themoviedb.org/movie/16869"
    },
    {
      "title": "I Saw the TV Glow",
      "year": 2024,
      "score": 9.6,
      "type": "film",
      "tmdb_url": "https://www.themoviedb.org/movie/858017"
    },
    {
      "title": "Citizen Kane",
      "year": 1941,
      "score": 9.6,
      "type": "film",
      "tmdb_url": null
    },
    {
      "title": "The Royal Tenenbaums",
      "year": 2001,
      "score": 9.5,
      "type": "film",
      "tmdb_url": "https://www.themoviedb.org/movie/9428"
    },
    {
      "title": "The Talented Mr. Ripley",
      "year": 1999,
      "score": 9.5,
      "type": "film",
      "tmdb_url": "https://www.themoviedb.org/movie/1213"
    },
    {
      "title": "The Nice Guys",
      "year": 2016,
      "score": 9.5,
      "type": "film",
      "tmdb_url": "https://www.themoviedb.org/movie/290250"
    },
    {
      "title": "L.A. Confidential",
      "year": 1997,
      "score": 9.5,
      "type": "film",
      "tmdb_url": "https://www.themoviedb.org/movie/2118"
    }
  ],
  "top_tv": [
    {
      "title": "Twin Peaks",
      "year": 1990,
      "score": 9.9,
      "type": "tv",
      "tmdb_url": "https://www.themoviedb.org/tv/1920"
    },
    {
      "title": "The Leftovers",
      "year": 2014,
      "score": 9.8,
      "type": "tv",
      "tmdb_url": "https://www.themoviedb.org/tv/54344"
    },
    {
      "title": "Mad Men",
      "year": 2007,
      "score": 9.8,
      "type": "tv",
      "tmdb_url": "https://www.themoviedb.org/tv/1104"
    },
    {
      "title": "Fargo",
      "year": 2014,
      "score": 9.7,
      "type": "tv",
      "tmdb_url": "https://www.themoviedb.org/tv/60622"
    },
    {
      "title": "Breaking Bad",
      "year": 2008,
      "score": 9.7,
      "type": "tv",
      "tmdb_url": "https://www.themoviedb.org/tv/1396"
    },
    {
      "title": "The Sopranos",
      "year": 1999,
      "score": 9.7,
      "type": "tv",
      "tmdb_url": "https://www.themoviedb.org/tv/1398"
    },
    {
      "title": "Veep",
      "year": 2012,
      "score": 9.6,
      "type": "tv",
      "tmdb_url": "https://www.themoviedb.org/tv/2947"
    },
    {
      "title": "Barry",
      "year": 2018,
      "score": 9.5,
      "type": "tv",
      "tmdb_url": "https://www.themoviedb.org/tv/73107"
    },
    {
      "title": "Watchmen",
      "year": 2019,
      "score": 9.5,
      "type": "tv",
      "tmdb_url": "https://www.themoviedb.org/tv/79788"
    },
    {
      "title": "The Pitt",
      "year": 2025,
      "score": 9.4,
      "type": "tv",
      "tmdb_url": "https://www.themoviedb.org/tv/250307"
    }
  ],
  "recently_watched": [
    {
      "title": "Twelve Monkeys",
      "year": 1995,
      "score": 9.4,
      "type": "film",
      "tmdb_url": "https://www.themoviedb.org/movie/63",
      "logged": "2026-07-04"
    },
    {
      "title": "Walk the Line",
      "year": 2005,
      "score": 8,
      "type": "film",
      "tmdb_url": "https://www.themoviedb.org/movie/69",
      "logged": "2026-07-04"
    },
    {
      "title": "Stranger Things",
      "year": 2016,
      "score": 7.1,
      "type": "tv",
      "tmdb_url": "https://www.themoviedb.org/tv/66732",
      "logged": "2026-07-03"
    },
    {
      "title": "Beavis and Butt-Head",
      "year": 1993,
      "score": 7.5,
      "type": "tv",
      "tmdb_url": "https://www.themoviedb.org/tv/13943",
      "logged": "2026-07-03"
    },
    {
      "title": "Orange Is the New Black",
      "year": 2013,
      "score": 6.5,
      "type": "tv",
      "tmdb_url": "https://www.themoviedb.org/tv/1424",
      "logged": "2026-07-03"
    }
  ],
  "recent_tv": [
    {
      "title": "Stranger Things",
      "year": 2016,
      "score": 7.1,
      "type": "tv",
      "tmdb_url": "https://www.themoviedb.org/tv/66732",
      "logged": "2026-07-03"
    },
    {
      "title": "Beavis and Butt-Head",
      "year": 1993,
      "score": 7.5,
      "type": "tv",
      "tmdb_url": "https://www.themoviedb.org/tv/13943",
      "logged": "2026-07-03"
    },
    {
      "title": "Orange Is the New Black",
      "year": 2013,
      "score": 6.5,
      "type": "tv",
      "tmdb_url": "https://www.themoviedb.org/tv/1424",
      "logged": "2026-07-03"
    },
    {
      "title": "Heroes",
      "year": 2006,
      "score": 7.1,
      "type": "tv",
      "tmdb_url": "https://www.themoviedb.org/tv/1639",
      "logged": "2026-07-03"
    },
    {
      "title": "The Good Place",
      "year": 2016,
      "score": 7.4,
      "type": "tv",
      "tmdb_url": "https://www.themoviedb.org/tv/66573",
      "logged": "2026-05-25"
    }
  ]
}
